clockify_mcp/__init__.py
clockify_mcp/client.py
clockify_mcp/server.py
clockify_mcp_server-0.1.0.dist-info/METADATA
clockify_mcp_server-0.1.0.dist-info/WHEEL
clockify_mcp_server-0.1.0.dist-info/entry_points.txt
clockify_mcp_server-0.1.0.dist-info/licenses/LICENSE
clockify_mcp_server-0.1.0.dist-info/RECORD
